{
"0":"२२२        वीरमित्रोदयस्य श्राद्धप्रकाशे-",
"1":"अत्राहरणस्य दृष्टार्थत्वाद् ब्राह्मणेभ्यस्तद्देयमित्युक्तं भवति ।",
"2":"एतद्गन्धादिदानं च देवतोद्देशेनैव तदधिष्ठानभूतद्विजकरे कर्त्तव्यम् ।",
"3":"न तु द्विजसम्प्रदानकमित्युक्तं सम्प्रदाननिर्णये ।",
"4":"याज्ञवल्क्येन तु गन्धादिदानस्योदक पूर्वकत्वमुक्तम् ।",
"5":"दत्वोदकं गन्धमाल्यं धूपदानं सदीपकम् ।",
"6":"गौतमेन तु विध्युपदिष्टानां सर्वदानानामुदकपूर्वकत्वमुक्तम्",
"7":"अन्नभिक्षादानमप्पूर्वम् । ददातिषु वैवधर्म्यग्विति । तथा सर्वा",
"8":"ण्युदक क  पूर्वाणि दानानि विहारवर्जमिति । अत्र विशेषो -",
"9":"ब्रह्मपुराणे---",
"10":"श्वेतचन्दन कर्पूरकुङ्कुमानि शुभानि तु ।",
"11":"विलेपनार्थ दद्यात्तु यच्चान्यत्पितृबल्लभम् । इति ।",
"12":"अत्र मन्त्रं विधिविशेषं चाह -",
"13":"व्यासः,",
"14":"विपवित्रक रो गन्धैर्गन्धद्वारेति पूजयेत् ।",
"15":"गन्धद्वारेति मन्त्रेण विप्रे गन्धान्प्रदापयेत् ।",
"16":"र्गन्धौर्वगत पवित्रकरः श्राद्धकर्ता विप्रान् पूजयेत्, ललाटगल.",
"17":"वक्षः कुक्षिकक्षाद्यङ्गेषु विलिम्पेदित्यर्थः । अत्र विपवित्रकर विधानं",
"18":"लेपनं कुर्वतः श्राद्धकर्त्तुरेव न पुनः करगृहीतगन्धैः स्वाङ्गविलेपनं",
"19":"कुर्वतां ब्राह्मणानामपि । अत एव वृद्धशातातपेन ।",
"20":"पवित्रं तु करे कृत्वा यः समालभते द्विजान् ।",
"21":"राक्षसानां भवेच्छ्राद्धं निराशाः पितरो गताः ॥ इति ।",
"22":"श्राद्धकर्त्तरि च विलेपनकारिणि सपवित्रकरे दोषोऽभिहितः ।",
"23":"समालम्भनम् = विलेपनम् ।",
"24":"केचित्तु ब्राह्मणा अपि स्वाङ्गविलेपनं कुर्वाणाः पवित्राणि विन्य",
"25":"से युरित्याहुः ।",
"26":"अत्र विशेषान्तरं देवलस्मृतिभविष्यत्पुराणयोः ।",
"27":"यज्ञोपवीतं विप्राणां स्कन्धात्रैवावतारयेत् ।",
"28":"गन्धादिपूजा सिद्ध्यर्थं दैवे पित्र्ये च कर्मणि ॥ इति ।",
"29":"यजमानो नावतारयेदित्यर्थः ।",
"30":"शातातपोऽपि,",
"31":"कट्यां त्रिपुष्करं कृत्वा गन्धैर्यस्तु विलिम्पति ।",
"32":"पितृयज्ञे नवे छिद्रं निराशैः पितृभिर्गतैः ॥ इति ।",
}