{
"0":"१९०                  वरिमित्रोदयस्य श्राद्धमका शे-",
"1":"अत्र विशेषः पैठीनखिनेोक्तः ।",
"2":"प्राङ्मुखान् विश्वेदेवानुपवेशयेत्, हविष्मत्सु आसनेषु पितॄन्",
"3":"दक्षिणपूर्वेणेति ।",
"4":"दक्षिणपूर्वेण दक्षिण पूर्वाभिमुखानित्यर्थः । अथवा देवब्राह्मणापे-",
"5":"क्षया दक्षिणस्यां दिशीत्यर्थ' ।",
"6":"हारीतेन तु । पित्र्यब्राह्मणानां पूर्वाभिमुखतया दैविकानां",
"7":"चोत्तराभिमुखतयोपवेशनमुक्तम् ।",
"8":"दक्षिणाग्रेषु दर्भेमु प्राङ्मुखान् भोजयेत् । उदङ्मुखान् वैश्व",
"9":"देवे इति ।",
"10":"बौधायनेनाप्युक्तम् ।",
"11":"सदर्भों पक्लृप्तेष्वासनेषु द्वौ द्वौ देवे, श्रीन् पित्र्ये, एकैकमुभयत्र",
"12":"वा प्राङ्मुखानुपवेशयेदुदङ्मुखान् वेति ।",
"13":"तदेवमत्र दिग्विशेषाभिमुख्ये पञ्च पक्षा भवन्ति । तत्र वैश्व-",
"14":"देविका: प्राङ्मुखाः, पिझ्यास्तूदङमुखा इत्येकः | [ वैश्वदेविका.",
"15":"प्राङ्मुखाः, पित्र्यास्तु दक्षिणपूर्वाभिमुखा इति द्वितीयः । वैश्वदे",
"16":"विका उत्तराभिमुखाः, पित्र्यास्तु प्राङ्मुखा इति तृतीयः । वैश्व",
"17":"देविकाः प्राङ्मुखाः, पित्र्यास्तदङ्मुखा इति चतुर्थ: ।] वैश्वदेविका",
"18":"उदङ्मुखाः पित्र्याः प्राङ्मुखा इति पञ्चमः । अत्र स्वस्वगृह्यानुसा",
"19":"रेण व्यवस्था | स्वगृहये विशेषानाम्नाते तु वैश्वदेविकानां प्राङ्मु•",
"20":"खत्वं पितृणामुदङ्मुखत्वमिति । अयमेव पक्षोऽङ्गीकर्तव्यो बहुस्मृति",
"21":"संमतः । अत्र दैवं प्रदक्षिणोपचारेण पितॄणामप्रदक्षिणोपचारेण का,",
"22":"र्यम् | "प्रदक्षिण तु देवाना पितॄणामप्रदक्षिण" मिति बौधायनोकेः ।",
"23":"तथा च कात्यायने ।",
"24":"पिण्डपितृयज्ञवदुपचारः पित्र्ये ।",
"25":"पित्र्ये= पितृब्राह्मणे | पिण्डपितृयज्ञवदुपचारः=पिण्डपितृयञ्चवत् क्रिया ।",
"26":"अपसव्यम् दक्षिणाभिमुखेन कर्तव्यम्, दक्षिणसंस्थ कर्तव्यमिति वा ।",
"27":"तथा च यमः ।",
"28":"दक्षिणसंस्था आसरिन् न स्पृशेयुः परस्परम् ॥ इति ।",
"29":"दक्षिणबाहुभागे संस्था येषां ते दक्षिणसंस्था इति विग्रहः । एतच",
"30":"ब्राह्मणपङ्केः पश्चिमोपक्रमप्रागपवर्गत्वे एवोपपद्यते । अत एवाह ।",
}